{
  "asn" : 6025,
  "metadata" : {
    "handle" : "DNIC-ASBLK-05800-06055",
    "description" : "United States Department of Defense (DoD)",
    "countryCode" : "US",
    "country" : "United States",
    "origin" : "authoritative",
    "lastAnnounced" : "2026-01-04T11:40:59.103467Z"
  },
  "prefixes" : {
    "ipv4" : [ ],
    "ipv6" : [
      "2608:141:c::/48",
      "2608:142:c::/48",
      "2608:4123:2::/48",
      "2608:4124:2::/48",
      "2608:c185:1::/48",
      "2608:c186:1::/48"
    ]
  }
}